django_oikotie/__init__.py
django_oikotie/apps.py
django_oikotie/enums.py
django_oikotie/oikotie.py
django_oikotie/utils.py
django_oikotie/xml_models/__init__.py
django_oikotie/xml_models/apartment.py
django_oikotie/xml_models/housing_company.py
django_oikotie-0.2.1.dist-info/LICENSE
django_oikotie-0.2.1.dist-info/METADATA
django_oikotie-0.2.1.dist-info/WHEEL
django_oikotie-0.2.1.dist-info/top_level.txt
django_oikotie-0.2.1.dist-info/RECORD
