Metadata-Version: 2.1
Name: django-oikotie
Version: 0.2.1
Summary: Django app for Oikotie integration.
Home-page: https://github.com/City-of-Helsinki/django-oikotie
Author: City of Helsinki
Author-email: dev@hel.fi
License: MIT License
Platform: UNKNOWN
Classifier: Environment :: Web Environment
Classifier: Framework :: Django
Classifier: Intended Audience :: Developers
Classifier: License :: OSI Approved :: MIT License
Classifier: Operating System :: OS Independent
Classifier: Programming Language :: Python
Classifier: Programming Language :: Python :: 3.8
Classifier: Topic :: Internet :: WWW/HTTP
Classifier: Topic :: Internet :: WWW/HTTP :: Dynamic Content
License-File: LICENSE
Requires-Dist: Django >=3.2
Requires-Dist: lxml >=4.6.3
